{"cameraMode":{"drawMode":0,"name":"Shaded","section":"Shading Mode"},"sceneLighting":false,"audioPlay":false,"sceneViewState":{"m_AlwaysRefresh":false,"showFog":true,"showSkybox":false,"showFlares":true,"showImageEffects":true,"showParticleSystems":true,"showVisualEffectGraphs":true,"m_FxEnabled":true},"in2DMode":false,"pivot":{"x":-1.347982406616211,"y":0.6792809367179871,"z":19.501296997070314},"rotation":{"x":0.055210769176483157,"y":-0.6924262046813965,"z":0.05329051613807678,"w":0.7173948884010315},"size":2.1123311519622804,"orthographic":false}